data_center_service/__init__.py
data_center_service/api/__init__.py
data_center_service/api/collections/__init__.py
data_center_service/api/collections/add_documents.py
data_center_service/api/collections/search_documents.py
data_center_service/client.py
data_center_service/errors.py
data_center_service/models/__init__.py
data_center_service/models/add_documents_request.py
data_center_service/models/add_documents_response.py
data_center_service/models/document_request.py
data_center_service/models/document_request_metadata.py
data_center_service/models/http_validation_error.py
data_center_service/models/search_response.py
data_center_service/models/search_result.py
data_center_service/models/search_result_metadata.py
data_center_service/models/validation_error.py
data_center_service/py.typed
data_center_service/types.py
data_center_service-0.3.0.dist-info/METADATA
data_center_service-0.3.0.dist-info/WHEEL
data_center_service-0.3.0.dist-info/RECORD
